Workbook

Sheet Assumptions
A1: ILLUSTRATIVE — owner to finalise
A2: Driver | B2: Year 1 | C2: Year 2 | D2: Year 3
A3: Team FTE | B3: 4 | C3: 6 | D3: 9
A4: Blended cost / FTE (£) | B4: 70000 | C4: 72000 | D4: 74000
A5: Infrastructure — on-device (low marginal cost) | B5: 12000 | C5: 24000 | D5: 48000
A6: Compliance / legal / audit (DCB0129, DPO, ICO, security) | B6: 40000 | C6: 45000 | D6: 50000
A7: Evidence / PPIE / research study | B7: 15000 | C7: 60000 | D7: 40000
A8: GTM / partnerships / marketing | B8: 20000 | C8: 50000 | D8: 90000
A9: Product / design / tooling / misc | B9: 15000 | C9: 20000 | D9: 25000
A10: Partnership seats (carers covered) | B10: 0 | C10: 1500 | D10: 9000
A11: Partnership price / carer / month (£) | B11: 3 | C11: 3 | D11: 3
A12: Supporter donations (£) | B12: 2000 | C12: 10000 | D12: 25000
A13: Edit the highlighted (yellow) cells — all downstream sheets recompute automatically.

Sheet Costs
A1: ILLUSTRATIVE — owner to finalise
A2: Cost line | B2: Year 1 | C2: Year 2 | D2: Year 3 | E2: 3-yr Total
A3: People (FTE × blended cost / FTE) | B3: ='Assumptions'!B3*'Assumptions'!B4 | C3: ='Assumptions'!C3*'Assumptions'!C4 | D3: ='Assumptions'!D3*'Assumptions'!D4 | E3: =B3+C3+D3
A4: Infrastructure (on-device → low marginal cost) | B4: ='Assumptions'!B5 | C4: ='Assumptions'!C5 | D4: ='Assumptions'!D5 | E4: =B4+C4+D4
A5: Compliance / legal / audit (DCB0129, DPO, ICO, security) | B5: ='Assumptions'!B6 | C5: ='Assumptions'!C6 | D5: ='Assumptions'!D6 | E5: =B5+C5+D5
A6: Evidence / PPIE / research study | B6: ='Assumptions'!B7 | C6: ='Assumptions'!C7 | D6: ='Assumptions'!D7 | E6: =B6+C6+D6
A7: GTM / partnerships / marketing | B7: ='Assumptions'!B8 | C7: ='Assumptions'!C8 | D7: ='Assumptions'!D8 | E7: =B7+C7+D7
A8: Product / design / tooling / misc | B8: ='Assumptions'!B9 | C8: ='Assumptions'!C9 | D8: ='Assumptions'!D9 | E8: =B8+C8+D8
A9: Total cost | B9: =SUM(B3:B8) | C9: =SUM(C3:C8) | D9: =SUM(D3:D8) | E9: =B9+C9+D9
A10: Illustrative: Y1≈£382k · Y2≈£631k · Y3≈£919k · 3-yr≈£1.93m (recomputes from Assumptions)

Sheet Funding & Revenue
A1: ILLUSTRATIVE — owner to finalise
A2: Source | B2: Year 1 | C2: Year 2 | D2: Year 3 | E2: 3-yr Total | F2: Note
A3: Grants (non-dilutive) | B3: 200000 | C3: 350000 | D3: 100000 | E3: =B3+C3+D3 | F3: SBRI Healthcare ≤£200k · NIHR Innovation Catalyst £150k · Innovate UK £200k
A4: Mission seed capital | B4: 400000 | C4: 400000 | D4: 0 | E4: =B4+C4+D4 | F4: Patient / mission investor(s) [owner-set]
A5: B2B2C partnership revenue | B5: ='Assumptions'!B10*'Assumptions'!B11*12 | C5: ='Assumptions'!C10*'Assumptions'!C11*12 | D5: ='Assumptions'!D10*'Assumptions'!D11*12 | E5: =B5+C5+D5 | F5: Seats × price/mo × 12 (Y2: 1,500×£3 · Y3: 9,000×£3)
A6: Optional supporter donations | B6: ='Assumptions'!B12 | C6: ='Assumptions'!C12 | D6: ='Assumptions'!D12 | E6: =B6+C6+D6 | F6: "Keep the light on" voluntary — never a paywall
A7: Total inflow | B7: =SUM(B3:B6) | C7: =SUM(C3:C6) | D7: =SUM(D3:D6) | E7: =B7+C7+D7

Sheet Cash Summary
A1: ILLUSTRATIVE — owner to finalise
B2: Year 1 | C2: Year 2 | D2: Year 3 | E2: Notes
A3: Total inflow | B3: ='Funding & Revenue'!B7 | C3: ='Funding & Revenue'!C7 | D3: ='Funding & Revenue'!D7 | E3: From Funding & Revenue
A4: Total cost | B4: ='Costs'!B9 | C4: ='Costs'!C9 | D4: ='Costs'!D9 | E4: From Costs
A5: Net cash (inflow − cost) | B5: =B3-B4 | C5: =C3-C4 | D5: =D3-D4 | E5: Positive = surplus · negative = gap requiring bridge capital
A6: Cumulative cash | B6: =B5 | C6: =C5+B6 | D6: =D5+C6 | E6: Rolling sum — shows when gap capital is needed
A7: Monthly burn (cost ÷ 12) | B7: =B4/12 | C7: =C4/12 | D7: =D4/12 | E7: People + compliance dominated · on-device removes per-user cost
A9: Funding-need analysis — 24-month bridge
A10: 24-month gross cost (Y1 + Y2) | B10: ='Costs'!B9+'Costs'!C9 | E10: ~£1.01m illustrative
A11: Grant coverage (Y1+Y2 grants only) | B11: =200000+350000 | E11: ~£550k (SBRI + NIHR + Innovate UK combined)
A12: Mission-seed bridge needed | B12: =B10-B11 | E12: ~£460k gap → blended ask ~£0.75m–£1.2m incl. buffer
A13: Runway to first partnership revenue | B13: ~18–24 months | E13: Key milestone: first B2B2C contract within the window
A14: Y3 net is negative (~−£470k illustrative): team scale-up precedes partnership-revenue ramp. This is where B2B2C revenue must accelerate, or a Series-seed / major grant tops up. See Scenarios sheet for Conservative / Stretch alternatives.

Sheet Scenarios
A1: ILLUSTRATIVE — owner to finalise
B3: BASE (plan as modelled) | E3: CONSERVATIVE (partnership slips) | H3: STRETCH (accelerated ramp)
A4: Line | B4: Y1 | C4: Y2 | D4: Y3 | E4: Y1 | F4: Y2 | G4: Y3 | H4: Y1 | I4: Y2 | J4: Y3
A5: Total inflow (£) | B5: 602000 | C5: 814000 | D5: 449000 | E5: 602000 | F5: 614000 | G5: 349000 | H5: 602000 | I5: 914000 | J5: 649000
A6: Total cost (£) | B6: 382000 | C6: 631000 | D6: 919000 | E6: 382000 | F6: 631000 | G6: 919000 | H6: 382000 | I6: 631000 | J6: 869000
A7: Net cash (£) | B7: 220000 | C7: 183000 | D7: -470000 | E7: 220000 | F7: -17000 | G7: -570000 | H7: 220000 | I7: 283000 | J7: -220000
A8: Cumulative cash (£) | B8: 220000 | C8: 403000 | D8: -67000 | E8: 220000 | F8: 203000 | G8: -367000 | H8: 220000 | I8: 503000 | J8: 283000
A9: B2B2C seats | B9: 0 | C9: 1500 | D9: 9000 | E9: 0 | F9: 0 | G9: 9000 | H9: 0 | I9: 3000 | J9: 15000
A10: B2B2C revenue (£) | B10: 0 | C10: 54000 | D10: 324000 | E10: 0 | F10: 0 | G10: 324000 | H10: 0 | I10: 108000 | J10: 540000
A12: Scenario notes
A13: BASE | B13: First B2B2C partnership Y2 (~1,500 seats). Grants + seed cover Y1–Y2. Y3 dip = team scale-up ahead of partnership-revenue ramp.
A14: CONSERVATIVE | B14: Partnership slips to Y3 (Y2 B2B2C revenue = £0). Y2 supporter donations −50%. Wider funding gap; larger seed or slower hiring needed.
A15: STRETCH | B15: 2 ICB/employer pilots in Y2 (~3,000 seats). Y3 ramps to ~15,000 seats + supporter donations ×2. Near-break-even in Y3.
A17: Unit economics — why the free model works at scale
A18: Marginal cost — one more carer | B18: ≈ £0 | C18: On-device inference: no cloud API call, no per-user compute cost after download
A19: Fixed cost base (team + compliance) | B19: £382k Y1 | C19: All users share this overhead — scale doesn't multiply it
A20: Partnership seat contribution | B20: ≈ £3/mo per seat | C20: Near-pure contribution to sustainability at near-zero marginal cost
A21: Model thesis | B21: Cover fixed base → | C21: then every partnership seat sold is almost wholly additive sustainability margin
